Workbook

Sheet 资产总览
A1: 个人外币 & 固收资产追踪
A3: 更新时间 | B3: =TODAY()
A5: 外汇持仓总成本(CNY) | B5: =SUM(外汇交易记录!I2:I100)
A6: 外汇当前总价值(CNY) | B6: =SUM(外汇交易记录!K2:K100)
A7: 外汇总盈亏(CNY) | B7: =SUM(外汇交易记录!L2:L100)
A9: 柜台债总成本(CNY) | B9: =SUM(柜台债持仓!G2:G100)
A10: 柜台债持有收益(CNY) | B10: =SUM(柜台债持仓!L2:L100)
A12: 合计总资产(CNY) | B12: =B6+SUM(柜台债持仓!K2:K100)
A13: 合计总盈亏(CNY) | B13: =B7+B10

Sheet 外汇交易记录
A1: 交易ID | B1: 交易时间 | C1: 卖出货币 | D1: 卖出金额 | E1: 买入货币 | F1: 买入金额 | G1: 隐含汇率 (卖出/买入) | H1: 基准货币 (CNY/USD) | I1: 买入金额(CNY) | J1: 当前汇率(CNY) | K1: 当前价值(CNY) | L1: 盈亏(CNY) | M1: 盈亏% | N1: 备注
A2: FX001 | B2: 2025-09-18 02:01:10 | C2: JPY | D2: 52792 | E2: USD | F2: 361.59 | G2: =IF(AND(D2<>"",F2<>""),D2/F2,"") | H2: USD | K2: =IF(AND(F2<>"",J2<>""),F2*J2,"") | L2: =IF(AND(K2<>"",I2<>""),K2-I2,"") | M2: =IF(AND(L2<>"",I2<>"",I2<>0),L2/I2,"") | N2: 卖日元买美元
A3: FX002 | B3: 2025-09-18 02:02:50 | C3: JPY | D3: 50000 | E3: USD | F3: 342.72 | G3: =IF(AND(D3<>"",F3<>""),D3/F3,"") | H3: USD | K3: =IF(AND(F3<>"",J3<>""),F3*J3,"") | L3: =IF(AND(K3<>"",I3<>""),K3-I3,"") | M3: =IF(AND(L3<>"",I3<>"",I3<>0),L3/I3,"") | N3: 卖日元买美元
A4: FX003 | B4: 2025-09-18 09:54:35 | C4: CNY | E4: USD | F4: 800 | G4: =IF(AND(D4<>"",F4<>""),D4/F4,"") | H4: CNY | K4: =IF(AND(F4<>"",J4<>""),F4*J4,"") | L4: =IF(AND(K4<>"",I4<>""),K4-I4,"") | M4: =IF(AND(L4<>"",I4<>"",I4<>0),L4/I4,"") | N4: 买美元（卖出CNY待补充）
A5: FX004 | B5: 2025-09-18 10:23:30 | C5: AUD | D5: 506.9 | E5: USD | F5: 336.58 | G5: =IF(AND(D5<>"",F5<>""),D5/F5,"") | H5: USD | K5: =IF(AND(F5<>"",J5<>""),F5*J5,"") | L5: =IF(AND(K5<>"",I5<>""),K5-I5,"") | M5: =IF(AND(L5<>"",I5<>"",I5<>0),L5/I5,"") | N5: 卖澳元买美元
A6: 汇总 | L6: =SUM(L2:L5)
A8: 📌 填写说明：蓝色列为手动输入；I列=买入时成本(CNY)；J列由Agent自动填入当前汇率；K/L/M为自动计算

Sheet 柜台债持仓
A1: 债券代码 | B1: 债券名称 | C1: 买入日期 | D1: 到期日 | E1: 面值(元) | F1: 买入价格 | G1: 买入成本(元) | H1: 票面利率% | I1: 已持有天数 | J1: 应计利息(元) | K1: 当前估值(元) | L1: 持有收益(元) | M1: 年化收益率 | N1: 备注
A2: 019735 | B2: 24附息国债35 | C2: 2024-10-15 | D2: 2027-10-15 | E2: 50000 | F2: 100 | G2: =E2*F2/100 | H2: 2.05 | I2: =IF(AND(C2<>"",TODAY()>C2),TODAY()-DATEVALUE(TEXT(C2,"YYYY-MM-DD")),"") | J2: =IF(AND(E2<>"",H2<>"",I2<>""),E2*H2/100/365*I2,"") | L2: =IF(AND(K2<>"",G2<>""),K2+J2-G2,"") | M2: =IF(AND(L2<>"",G2<>"",I2<>"",I2>0),L2/G2/I2*365,"") | N2: 示例，请核对后修改
A4: 📌 填写说明：蓝色列手动输入；G列=买入成本自动计算；I列=已持有天数自动算；J列=当前市场估值(Agent填入)；K/L/M自动计算
